{
  "project": {
    "name": "Ultimate Dominion",
    "description": "A medieval fantasy trading card game with blockchain integration",
    "repository": "ultimate-dominion/ultimate-dominion"
  },
  "documentation": {
    "style": {
      "language": "simple and narrative",
      "technical_terms": "must be explained with real-world analogies",
      "format": {
        "primary": "markdown with ASCII diagrams",
        "rules": [
          "Use paragraph form for all explanations",
          "No bullet points or numbered lists allowed",
          "Every diagram must be explained in narrative form",
          "Use real-world analogies to explain technical concepts",
          "Keep language simple and accessible"
        ]
      },
      "required_sections": [
        "overview",
        "how it works",
        "examples",
        "technical details"
      ]
    },
    "required_files": [
      {
        "name": "frontend_guidelines.md",
        "contents": [
          "design philosophy",
          "color palette",
          "typography",
          "icons",
          "component design",
          "layout guidelines",
          "animations",
          "accessibility",
          "performance"
        ]
      },
      {
        "name": "backend_structure.md",
        "contents": [
          "system architecture",
          "api routes",
          "data flow",
          "environments",
          "deployment",
          "monitoring",
          "performance",
          "security"
        ]
      },
      {
        "name": "technical_architecture.md",
        "contents": [
          "system overview",
          "component interactions",
          "data models",
          "security measures",
          "scalability approach"
        ]
      },
      {
        "name": "app_flow_document.md",
        "contents": [
          "user journeys",
          "game mechanics",
          "screen flows",
          "interaction patterns"
        ]
      }
    ]
  },
  "development": {
    "environments": {
      "local": {
        "frontend": "http://localhost:5173",
        "api": "http://localhost:8080",
        "purpose": "development and testing"
      },
      "staging": {
        "frontend": "ultimate-dominion-staging.vercel.app",
        "api": "ultimate-dominion-api.onrender.com",
        "purpose": "pre-production testing"
      },
      "production": {
        "frontend": "ultimate-dominion.vercel.app",
        "api": "ultimate-dominion-api.onrender.com",
        "purpose": "live deployment"
      }
    },
    "code_style": {
      "frontend": {
        "framework": "React with TypeScript",
        "state_management": "Zustand",
        "styling": "Tailwind CSS",
        "component_structure": "atomic design"
      },
      "backend": {
        "framework": "Express.js",
        "deployment": "Vercel Serverless",
        "blockchain": "MUD framework",
        "storage": "IPFS via Pinata"
      }
    },
    "deployment_rules": {
      "pre_deploy_checks": [
        "run all tests",
        "check environment variables",
        "verify smart contracts",
        "test API endpoints",
        "check frontend builds",
        "verify IPFS connections"
      ],
      "post_deploy_checks": [
        "monitor error rates",
        "check response times",
        "verify blockchain state",
        "test critical user flows",
        "monitor resource usage"
      ]
    },
    "security_rules": {
      "required": [
        "validate all requests",
        "authenticate users via wallet",
        "authorize actions",
        "sanitize inputs",
        "rate limit requests",
        "verify blockchain transactions"
      ],
      "environment_variables": {
        "required": [
          "PINATA_JWT",
          "PRIVATE_KEY",
          "WORLD_ADDRESS",
          "INITIAL_BLOCK_NUMBER",
          "RPC_URL"
        ],
        "optional": [
          "DEBUG_MODE",
          "RATE_LIMIT_WINDOW",
          "CACHE_TTL"
        ]
      }
    },
    "performance_targets": {
      "api_response_time": "< 200ms",
      "page_load_time": "< 2s",
      "time_to_interactive": "< 3s",
      "blockchain_confirmation": "< 5s"
    }
  },
  "git": {
    "branch_naming": {
      "feature": "feature/*",
      "bugfix": "bugfix/*",
      "hotfix": "hotfix/*",
      "release": "release/*"
    },
    "commit_message_format": {
      "type": ["feat", "fix", "docs", "style", "refactor", "test", "chore"],
      "scope": "optional",
      "template": "<type>(<scope>): <description>"
    },
    "review_requirements": {
      "required_approvals": 1,
      "checks": [
        "lint",
        "test",
        "build",
        "type-check"
      ]
    }
  }
}
