{
  "magicDamage": [
    {
      "effectId": "0xeee09063621624b3000000000000000000000000000000000000000000000000",
      "name": "basic magic attack",
      "stats": {
        "attackModifierBonus": 0,
        "bonusDamage": 0,
        "critChanceBonus": 0
      }
    },
    {
      "effectId": "0x2e0e6d5039f8c272000000000000000000000000000000000000000000000000",
      "name": "basic magic heal",
      "stats": {
        "attackModifierBonus": 0,
        "bonusDamage": 0,
        "critChanceBonus": 0
      }
    }
  ],
  "physicalDamage": [
    {
      "effectId": "0xbeeab8b096ac11af000000000000000000000000000000000000000000000000",
      "name": "basic weapon attack",
      "stats": {
        "armorPenetration": 0,
        "attackModifierBonus": 0,
        "bonusDamage": 0,
        "critChanceBonus": 0
      }
    }
  ],
  "statusEffects": [
    {
      "effectId": "0xd2812fe9b0b2cad2000000000000000000000000000000000000000000000000",
      "name": "blind",
      "stats": {
        "agiModifier": -8,
        "armorModifier": 0,
        "damagePerTick": 0,
        "hpModifier": 0,
        "intModifier": 0,
        "resistanceStat": 1,
        "strModifier": 0
      },
      "validity": {
        "cooldown": 3,
        "maxStacks": 1,
        "validTime": 0,
        "validTurns": 2
      }
    },
    {
      "effectId": "0x78ded5c390ab6de3000000000000000000000000000000000000000000000000",
      "name": "poison",
      "stats": {
        "agiModifier": 0,
        "armorModifier": 0,
        "damagePerTick": 1,
        "hpModifier": 0,
        "intModifier": 0,
        "resistanceStat": 1,
        "strModifier": 0
      },
      "validity": {
        "cooldown": 2,
        "maxStacks": 1,
        "validTime": 0,
        "validTurns": 2
      }
    },
    {
      "effectId": "0x54a7e38986f19669000000000000000000000000000000000000000000000000",
      "name": "stupify",
      "stats": {
        "agiModifier": 0,
        "armorModifier": 0,
        "damagePerTick": 0,
        "hpModifier": 0,
        "intModifier": -8,
        "resistanceStat": 1,
        "strModifier": 0
      },
      "validity": {
        "cooldown": 3,
        "maxStacks": 1,
        "validTime": 0,
        "validTurns": 2
      }
    },
    {
      "effectId": "0x98562f2b32aeb98f000000000000000000000000000000000000000000000000",
      "name": "weaken",
      "stats": {
        "agiModifier": 0,
        "armorModifier": 0,
        "damagePerTick": 0,
        "hpModifier": 0,
        "intModifier": 0,
        "resistanceStat": 1,
        "strModifier": -8
      },
      "validity": {
        "cooldown": 3,
        "maxStacks": 1,
        "validTime": 0,
        "validTurns": 2
      }
    }
  ]
}
